uam/__init__.py
uam/__main__.py
uam/__version__.py
uam/settings.py
uam/adapters/__init__.py
uam/adapters/database/__init__.py
uam/adapters/database/exceptions.py
uam/adapters/database/gateway.py
uam/adapters/database/models.py
uam/adapters/docker/__init__.py
uam/adapters/docker/exceptions.py
uam/adapters/docker/gateway.py
uam/entities/__init__.py
uam/entities/app.py
uam/entities/system.py
uam/entities/tap.py
uam/entities/exceptions/__init__.py
uam/entities/exceptions/app.py
uam/entities/exceptions/tap.py
uam/interfaces/__init__.py
uam/interfaces/cli/__init__.py
uam/interfaces/cli/app.py
uam/interfaces/cli/helper.py
uam/interfaces/cli/system.py
uam/interfaces/cli/tap.py
uam/usecases/__init__.py
uam/usecases/app.py
uam/usecases/system.py
uam/usecases/tap.py
uam/usecases/exceptions/__init__.py
uam/usecases/exceptions/app.py
uam/usecases/exceptions/tap.py
uam-0.1.0.dist-info/DESCRIPTION.rst
uam-0.1.0.dist-info/METADATA
uam-0.1.0.dist-info/RECORD
uam-0.1.0.dist-info/WHEEL
uam-0.1.0.dist-info/entry_points.txt
uam-0.1.0.dist-info/metadata.json
uam-0.1.0.dist-info/pbr.json
uam-0.1.0.dist-info/top_level.txt
